Workbook

Sheet 📊 Cuadro de Mandos
A1: 🌿 HUERTA ONLINE · CUADRO DE MANDOS
A2: =TEXT(TODAY(),"DD/MM/YYYY") -> 24/06/2026
A4: 📈 RESUMEN GENERAL
A5: Pedidos este mes | C5: Facturación este mes | E5: Clientes activos | G5: Satisfacción media | I5: Total facturado (histórico) | K5: Pedidos pendientes
A6: =COUNTIFS(Pedidos!B:B,">="&DATE(YEAR(TODAY()),MONTH(TODAY()),1),Pedidos!B:B,"<="&EOMONTH(TODAY(),0)) -> 0 | C6: =SUMIFS(Pedidos!H:H,Pedidos!B:B,">="&DATE(YEAR(TODAY()),MONTH(TODAY()),1),Pedidos!B:B,"<="&EOMONTH(TODAY(),0)) -> 0 | E6: =COUNTIF(Clientes!F:F,"Activo") -> 4 | G6: =IFERROR(AVERAGE(Satisfacción!E:E),0) -> 4.2 | I6: =SUMIF(Pedidos!I:I,"<>Cancelado",Pedidos!H:H) -> 137 | K6: =COUNTIF(Pedidos!I:I,"Pendiente") -> 2
A8: 🧺 CESTAS MÁS VENDIDAS | G8: 📦 ESTADO DE PEDIDOS
A9: Cesta | B9: Unidades vendidas | C9: Ingresos (€) | D9: % sobre total | G9: Estado | J9: Nº Pedidos | K9: Importe (€)
A10: Cesta Primavera S | B10: =COUNTIF(Pedidos!F:F,"Cesta Primavera S") -> 3 | C10: =SUMIF(Pedidos!F:F,"Cesta Primavera S",Pedidos!H:H) -> 72 | D10: =IFERROR(SUMIF(Pedidos!F:F,"Cesta Primavera S",Pedidos!H:H)/SUMIF(Pedidos!I:I,"<>Cancelado",Pedidos!H:H),0) -> 0.52554745 | G10: Pendiente | J10: =COUNTIF(Pedidos!I:I,"Pendiente") -> 2 | K10: =SUMIF(Pedidos!I:I,"Pendiente",Pedidos!H:H) -> 43
A11: Cesta Primavera M | B11: =COUNTIF(Pedidos!F:F,"Cesta Primavera M") -> 2 | C11: =SUMIF(Pedidos!F:F,"Cesta Primavera M",Pedidos!H:H) -> 50 | D11: =IFERROR(SUMIF(Pedidos!F:F,"Cesta Primavera M",Pedidos!H:H)/SUMIF(Pedidos!I:I,"<>Cancelado",Pedidos!H:H),0) -> 0.3649635 | G11: Entregado | J11: =COUNTIF(Pedidos!I:I,"Entregado") -> 4 | K11: =SUMIF(Pedidos!I:I,"Entregado",Pedidos!H:H) -> 94
A12: Cesta Verano S | B12: =COUNTIF(Pedidos!F:F,"Cesta Verano S") -> 0 | C12: =SUMIF(Pedidos!F:F,"Cesta Verano S",Pedidos!H:H) -> 0 | D12: =IFERROR(SUMIF(Pedidos!F:F,"Cesta Verano S",Pedidos!H:H)/SUMIF(Pedidos!I:I,"<>Cancelado",Pedidos!H:H),0) -> 0 | G12: Cobrado | J12: =COUNTIF(Pedidos!I:I,"Cobrado") -> 0 | K12: =SUMIF(Pedidos!I:I,"Cobrado",Pedidos!H:H) -> 0
A13: Cesta Verano M | B13: =COUNTIF(Pedidos!F:F,"Cesta Verano M") -> 0 | C13: =SUMIF(Pedidos!F:F,"Cesta Verano M",Pedidos!H:H) -> 0 | D13: =IFERROR(SUMIF(Pedidos!F:F,"Cesta Verano M",Pedidos!H:H)/SUMIF(Pedidos!I:I,"<>Cancelado",Pedidos!H:H),0) -> 0 | G13: Cancelado | J13: =COUNTIF(Pedidos!I:I,"Cancelado") -> 0 | K13: =SUMIF(Pedidos!I:I,"Cancelado",Pedidos!H:H) -> 0
A14: Cesta Sorpresa | B14: =COUNTIF(Pedidos!F:F,"Cesta Sorpresa") -> 1 | C14: =SUMIF(Pedidos!F:F,"Cesta Sorpresa",Pedidos!H:H) -> 15 | D14: =IFERROR(SUMIF(Pedidos!F:F,"Cesta Sorpresa",Pedidos!H:H)/SUMIF(Pedidos!I:I,"<>Cancelado",Pedidos!H:H),0) -> 0.10948905
A16: ⭐ SATISFACCIÓN DE CLIENTES | G16: 🚨 ALERTAS
A17: Media general | E17: =IFERROR(AVERAGE(Satisfacción!E:E),0) -> 4.2 | G17: Pedidos pendientes > 5 | J17: =IF(COUNTIF(Pedidos!I:I,"Pendiente")>5,"⚠️ REVISAR","✅ OK") -> ✅ OK
A18: Valoraciones 5⭐ | E18: =COUNTIF(Satisfacción!E:E,5) -> 2 | G18: Satisfacción < 3.5 (media) | J18: =IF(IFERROR(AVERAGE(Satisfacción!E:E),5)<3.5,"⚠️ ATENCIÓN","✅ OK") -> ✅ OK
A19: Valoraciones 4⭐ | E19: =COUNTIF(Satisfacción!E:E,4) -> 2 | G19: Clientes sin pedir (30 días) | J19: =COUNTIFS(Clientes!F:F,"Activo")&" activos (verificar manualmente)" -> 4 activos (verificar manualmente)
A20: Valoraciones ≤3 | E20: =COUNTIF(Satisfacción!E:E,"<=3") -> 1 | G20: Última cesta anunciada | J20: =IFERROR(TEXT(MAX(Cestas!F:F),"DD/MM/YYYY"),"Sin datos") -> 30/12/1899
A21: Repetirían (Sí) | E21: =COUNTIF(Satisfacción!F:F,"Sí") -> 4 | G21: Próximo anuncio (estimado) | J21: =IFERROR(TEXT(MAX(Cestas!F:F)+15,"DD/MM/YYYY"),"Sin datos") -> 14/01/1900
A22: Total respuestas | E22: =COUNTA(Satisfacción!E:E)-1 -> 5
A24: 📱 PLANTILLA MENSAJE WHATSAPP (copiar y editar)
A25: Hola [NOMBRE] 👋 🌿 ¡Ya está disponible nuestra nueva cesta de temporada! 🧺 [NOMBRE CESTA] — [PRECIO]€ Incluye: [PRODUCTOS] Si quieres tu cesta, respóndeme antes del [FECHA LÍMITE] con: ✅ Quiero 1 cesta / ✅ Quiero 2 cestas Entrega el [FECHA ENTREGA] en tu domicilio. ¡Muchas gracias por confiar en nuestra huerta! 🌱

Sheet Clientes
A1: 🌿 HUERTA ONLINE · CLIENTES
A2: ID | B2: Nombre | C2: Teléfono | D2: Dirección | E2: Zona | F2: Estado | G2: Fecha Alta | H2: Notas
A3: 1 | B3: María García | C3: 600 111 222 | D3: Calle Mayor 5 | E3: Centro | F3: Activo | G3: 2024-01-10 | H3: Prefiere cestas pequeñas
A4: 2 | B4: Juan López | C4: 611 333 444 | D4: Av. del Mar 12 | E4: Norte | F4: Activo | G4: 2024-02-15 | H4: Alérgico a berenjenas
A5: 3 | B5: Ana Martínez | C5: 622 555 666 | D5: C/ Rosal 8 | E5: Sur | F5: Activo | G5: 2024-03-01
A6: 4 | B6: Pedro Ruiz | C6: 633 777 888 | D6: Plaza Nueva 3 | E6: Centro | F6: Inactivo | G6: 2023-11-20 | H6: Pausa hasta mayo
A7: 5 | B7: Laura Sánchez | C7: 644 999 000 | D7: C/ Pinos 22 | E7: Este | F7: Activo | G7: 2024-04-05

Sheet Cestas
A1: 🧺 HUERTA ONLINE · CESTAS DE TEMPORADA
A2: ID Cesta | B2: Nombre | C2: Temporada | D2: Productos incluidos | E2: Precio (€) | F2: Fecha Anuncio | G2: Estado
A3: 1 | B3: Cesta Primavera S | C3: Primavera | D3: Lechugas, espinacas, rábanos, zanahorias, guisantes | E3: 18 | F3: 2024-04-01 | G3: Disponible
A4: 2 | B4: Cesta Primavera M | C4: Primavera | D4: Lechugas, espinacas, rábanos, zanahorias, guisantes, acelgas, apio | E4: 25 | F4: 2024-04-01 | G4: Disponible
A5: 3 | B5: Cesta Verano S | C5: Verano | D5: Tomates, pepinos, pimientos, calabacines, berenjenas | E5: 18 | F5: 2024-06-01 | G5: Próxima
A6: 4 | B6: Cesta Verano M | C6: Verano | D6: Tomates, pepinos, pimientos, calabacines, berenjenas, melón, judías verdes | E6: 26 | F6: 2024-06-01 | G6: Próxima
A7: 5 | B7: Cesta Sorpresa | C7: Todo el año | D7: Selección del día según cosecha | E7: 15 | G7: Disponible

Sheet Pedidos
A1: 📦 HUERTA ONLINE · PEDIDOS
A2: ID Pedido | B2: Fecha | C2: ID Cliente | D2: Nombre Cliente | E2: ID Cesta | F2: Cesta | G2: Cantidad | H2: Importe (€) | I2: Estado
A3: 1001 | B3: 2024-04-03 | C3: 1 | D3: María García | E3: 1 | F3: Cesta Primavera S | G3: 1 | H3: 18 | I3: Entregado
A4: 1002 | B4: 2024-04-03 | C4: 2 | D4: Juan López | E4: 2 | F4: Cesta Primavera M | G4: 1 | H4: 25 | I4: Entregado
A5: 1003 | B5: 2024-04-03 | C5: 3 | D5: Ana Martínez | E5: 1 | F5: Cesta Primavera S | G5: 2 | H5: 36 | I5: Entregado
A6: 1004 | B6: 2024-04-17 | C6: 1 | D6: María García | E6: 5 | F6: Cesta Sorpresa | G6: 1 | H6: 15 | I6: Entregado
A7: 1005 | B7: 2024-04-17 | C7: 5 | D7: Laura Sánchez | E7: 2 | F7: Cesta Primavera M | G7: 1 | H7: 25 | I7: Pendiente
A8: 1006 | B8: 2024-05-02 | C8: 2 | D8: Juan López | E8: 1 | F8: Cesta Primavera S | G8: 1 | H8: 18 | I8: Pendiente

Sheet Satisfacción
A1: ⭐ HUERTA ONLINE · SATISFACCIÓN DE CLIENTES
A2: Fecha | B2: ID Cliente | C2: Nombre | D2: Cesta valorada | E2: Valoración (1-5) | F2: Volvería a pedir | G2: Comentario
A3: 2024-04-08 | B3: 1 | C3: María García | D3: Cesta Primavera S | E3: 5 | F3: Sí | G3: Productos fresquísimos, muy contenta
A4: 2024-04-08 | B4: 2 | C4: Juan López | D4: Cesta Primavera M | E4: 4 | F4: Sí | G4: Buena variedad, alguna hoja mustia
A5: 2024-04-08 | B5: 3 | C5: Ana Martínez | D5: Cesta Primavera S | E5: 5 | F5: Sí | G5: Perfecto, repetiré seguro
A6: 2024-04-22 | B6: 1 | C6: María García | D6: Cesta Sorpresa | E6: 4 | F6: Sí | G6: Me encantó la sorpresa
A7: 2024-04-22 | B7: 5 | C7: Laura Sánchez | D7: Cesta Primavera M | E7: 3 | F7: Quizás | G7: Llegó tarde, esperaba más variedad
