Workbook

Sheet Satisfaccion
A1: ☕ CaféDigital — Encuesta de Satisfacción de Clientes
A2: Módulo 1 · Fuente: Formulario Google Forms / Microsoft Forms
A4: Fecha | B4: Hora | C4: Producto | D4: Calificacion (1-5) | E4: Regresaria | F4: Comentario
A5: 01/03/2024 | B5: 10:00 | C5: Sándwich | D5: 3 | E5: Sí | F5: Podría mejorar
A6: 02/03/2024 | B6: 18:30 | C6: Capuchino | D6: 4 | E6: Sí | F6: Me encantó
A7: 03/03/2024 | B7: 07:45 | C7: Torta de chocolate | D7: 3 | E7: Sí | F7: Nada especial
A8: 04/03/2024 | B8: 16:00 | C8: Café expreso | D8: 4 | E8: Sí | F8: Todo perfecto
A9: 05/03/2024 | B9: 18:00 | C9: Café expreso | D9: 4 | E9: Sí | F9: Me encantó
A10: 06/03/2024 | B10: 10:30 | C10: Té frío | D10: 4 | E10: Sí | F10: Todo perfecto
A11: 07/03/2024 | B11: 18:00 | C11: Sándwich | D11: 3 | E11: Sí | F11: El sándwich estaba frío
A12: 08/03/2024 | B12: 11:30 | C12: Capuchino | D12: 5 | E12: Sí | F12: Excelente atención
A13: 09/03/2024 | B13: 12:00 | C13: Café expreso | D13: 5 | E13: Sí | F13: Rico y rápido
A14: 10/03/2024 | B14: 13:00 | C14: Sándwich | D14: 3 | E14: Sí
A15: 11/03/2024 | B15: 08:10 | C15: Té frío | D15: 2 | E15: No | F15: Nada especial
A16: 12/03/2024 | B16: 12:00 | C16: Té frío | D16: 3 | E16: Sí | F16: Regular
A17: 13/03/2024 | B17: 17:30 | C17: Té frío | D17: 4 | E17: Sí | F17: Muy buen café
A18: 14/03/2024 | B18: 10:00 | C18: Capuchino | D18: 5 | E18: Sí | F18: Muy buen café
A19: 15/03/2024 | B19: 17:00 | C19: Torta de chocolate | D19: 5 | E19: Sí | F19: Volveré seguro
A20: 16/03/2024 | B20: 09:45 | C20: Sándwich | D20: 4 | E20: Sí | F20: Rico y rápido
A21: 17/03/2024 | B21: 17:00 | C21: Sándwich | D21: 4 | E21: Sí | F21: Me encantó
A22: 18/03/2024 | B22: 18:30 | C22: Café expreso | D22: 4 | E22: Sí | F22: Todo perfecto
A23: 19/03/2024 | B23: 17:00 | C23: Capuchino | D23: 5 | E23: Sí | F23: Rico y rápido
A24: 20/03/2024 | B24: 07:45 | C24: Sándwich | D24: 4 | E24: Sí | F24: Rico y rápido
A25: 21/03/2024 | B25: 12:15 | C25: Capuchino | D25: 3 | E25: Sí | F25: Podría mejorar
A26: 22/03/2024 | B26: 18:00 | C26: Capuchino | D26: 4 | E26: Sí | F26: Todo perfecto
... A36: 06/03/2024 | B36: 12:45 | C36: Sándwich | D36: 5 | E36: Sí | F36: Rico y rápido
A37: 07/03/2024 | B37: 18:30 | C37: Café expreso | D37: 3 | E37: Sí
A38: 08/03/2024 | B38: 14:00 | C38: Capuchino | D38: 5 | E38: Sí | F38: Excelente atención
A39: 09/03/2024 | B39: 17:00 | C39: Torta de chocolate | D39: 3 | E39: Sí | F39: Podría mejorar
A40: 10/03/2024 | B40: 09:20 | C40: Té frío | D40: 4 | E40: Sí | F40: Rico y rápido
A41: 11/03/2024 | B41: 07:15 | C41: Té frío | D41: 3 | E41: Sí | F41: Regular
A42: 12/03/2024 | B42: 12:00 | C42: Té frío | D42: 5 | E42: Sí | F42: Muy buen café
A43: 13/03/2024 | B43: 10:00 | C43: Torta de chocolate | D43: 3 | E43: Sí | F43: Podría mejorar
A44: 14/03/2024 | B44: 08:10 | C44: Café expreso | D44: 3 | E44: Sí | F44: Un poco lento
A45: 15/03/2024 | B45: 08:55 | C45: Sándwich | D45: 3 | E45: Sí | F45: Regular
A46: 16/03/2024 | B46: 09:20 | C46: Café expreso | D46: 5 | E46: Sí | F46: Todo perfecto
A47: 17/03/2024 | B47: 09:45 | C47: Capuchino | D47: 3 | E47: Sí | F47: Nada especial
A48: 18/03/2024 | B48: 09:45 | C48: Torta de chocolate | D48: 4 | E48: Sí | F48: Me encantó
A49: 19/03/2024 | B49: 17:00 | C49: Sándwich | D49: 5 | E49: Sí | F49: Me encantó
... A71: 15/03/2024 | B71: 11:00 | C71: Sándwich | D71: 5 | E71: Sí | F71: Excelente atención
A72: 16/03/2024 | B72: 14:30 | C72: Capuchino | D72: 3 | E72: Sí
A73: 17/03/2024 | B73: 15:00 | C73: Café expreso | D73: 5 | E73: Sí | F73: Muy buen café
A74: 18/03/2024 | B74: 09:20 | C74: Té frío | D74: 2 | E74: No | F74: Regular
A75: 19/03/2024 | B75: 09:20 | C75: Café expreso | D75: 5 | E75: Sí | F75: Super bueno
A76: 20/03/2024 | B76: 12:15 | C76: Café expreso | D76: 3 | E76: Sí | F76: El sándwich estaba frío
A77: 21/03/2024 | B77: 15:00 | C77: Café expreso | D77: 2 | E77: No | F77: El sándwich estaba frío
A78: 22/03/2024 | B78: 17:30 | C78: Té frío | D78: 4 | E78: Sí | F78: Volveré seguro
A79: 23/03/2024 | B79: 09:45 | C79: Té frío | D79: 5 | E79: Sí | F79: Rico y rápido
A80: 24/03/2024 | B80: 12:15 | C80: Sándwich | D80: 5 | E80: Sí | F80: Rico y rápido
A81: 25/03/2024 | B81: 11:30 | C81: Café expreso | D81: 4 | E81: Sí | F81: Volveré seguro
A82: 26/03/2024 | B82: 13:00 | C82: Torta de chocolate | D82: 2 | E82: No | F82: Un poco lento
A83: 01/03/2024 | B83: 08:10 | C83: Sándwich | D83: 4 | E83: Sí | F83: Muy buen café
A84: 02/03/2024 | B84: 12:00 | C84: Té frío | D84: 5 | E84: Sí | F84: Excelente atención
A85: 03/03/2024 | B85: 11:00 | C85: Torta de chocolate | D85: 3 | E85: Sí | F85: Podría mejorar
A86: 04/03/2024 | B86: 11:00 | C86: Café expreso | D86: 3 | E86: Sí
A87: 05/03/2024 | B87: 14:00 | C87: Sándwich | D87: 2 | E87: No
A88: 06/03/2024 | B88: 17:30 | C88: Café expreso | D88: 3 | E88: Sí | F88: Podría mejorar
A89: 07/03/2024 | B89: 08:30 | C89: Café expreso | D89: 3 | E89: Sí | F89: Podría mejorar
A90: 08/03/2024 | B90: 10:30 | C90: Torta de chocolate | D90: 4 | E90: Sí | F90: Excelente atención
A91: 09/03/2024 | B91: 09:45 | C91: Capuchino | D91: 4 | E91: Sí | F91: Rico y rápido
A92: 10/03/2024 | B92: 13:30 | C92: Sándwich | D92: 3 | E92: Sí | F92: Regular
A93: 11/03/2024 | B93: 08:10 | C93: Capuchino | D93: 2 | E93: No | F93: Un poco lento
A94: 12/03/2024 | B94: 07:15 | C94: Sándwich | D94: 3 | E94: Sí | F94: Un poco lento

Sheet Ventas
A1: ☕ CaféDigital — Registro de Ventas Diarias
A2: Módulo 2 · Fuente: Exportación CSV desde caja registradora
A4: Fecha | B4: Hora | C4: Producto | D4: Cantidad | E4: Precio_Unitario | F4: Total_Venta | G4: Mes
A5: 01/03/2024 | B5: 12:15 | C5: Capuchino | D5: 1 | E5: 4500 | F5: 4500 | G5: Marzo 2024
A6: 02/03/2024 | B6: 14:30 | C6: Sándwich | D6: 1 | E6: 6500 | F6: 6500 | G6: Marzo 2024
A7: 03/03/2024 | B7: 07:45 | C7: Café expreso | D7: 2 | E7: 3500 | F7: 7000 | G7: Marzo 2024
A8: 04/03/2024 | B8: 07:45 | C8: Torta de chocolate | D8: 1 | E8: 5500 | F8: 5500 | G8: Marzo 2024
A9: 05/03/2024 | B9: 08:10 | C9: Café expreso | D9: 2 | E9: 3500 | F9: 7000 | G9: Marzo 2024
A10: 06/03/2024 | B10: 12:45 | C10: Capuchino | D10: 2 | E10: 4500 | F10: 9000 | G10: Marzo 2024
A11: 07/03/2024 | B11: 08:30 | C11: Café expreso | D11: 2 | E11: 3500 | F11: 7000 | G11: Marzo 2024
A12: 08/03/2024 | B12: 17:00 | C12: Torta de chocolate | D12: 3 | E12: 5500 | F12: 16500 | G12: Marzo 2024
A13: 09/03/2024 | B13: 15:00 | C13: Sándwich | D13: 1 | E13: 6500 | F13: 6500 | G13: Marzo 2024
A14: 10/03/2024 | B14: 10:00 | C14: Sándwich | D14: 1 | E14: 6500 | F14: 6500 | G14: Marzo 2024
A15: 11/03/2024 | B15: 11:00 | C15: Café expreso | D15: 1 | E15: 3500 | F15: 3500 | G15: Marzo 2024
A16: 12/03/2024 | B16: 08:30 | C16: Capuchino | D16: 2 | E16: 4500 | F16: 9000 | G16: Marzo 2024
... A124: 30/03/2024 | B124: 08:10 | C124: Capuchino | D124: 1 | E124: 4500 | F124: 4500 | G124: Marzo 2024
A125: TOTAL | D125: =SUM(D5:D124) | F125: =SUM(F5:F124)

Sheet Compras
A1: ☕ CaféDigital — Reporte de Compras a Proveedores (ERP)
A2: Módulo 3 · Fuente: Exportación de sistema ERP del proveedor
A4: Fecha_Compra | B4: Ingrediente | C4: Proveedor | D4: Cantidad_kg | E4: Costo_Total_COP | F4: Mes
A5: 05/03/2024 | B5: Café en grano | C5: Distribuidora La Cosecha | D5: 5 | E5: 75000 | F5: Marzo 2024
A6: 04/03/2024 | B6: Leche entera | C6: Lácteos del Norte | D6: 20 | E6: 48000 | F6: Marzo 2024
A7: 06/03/2024 | B7: Té verde surtido | C7: Importadora Oriente | D7: 3 | E7: 36000 | F7: Marzo 2024
A8: 06/03/2024 | B8: Pan artesanal | C8: Panadería San Luis | D8: 10 | E8: 45000 | F8: Marzo 2024
A9: 06/03/2024 | B9: Harina de trigo | C9: Molinos Bogotá | D9: 8 | E9: 24000 | F9: Marzo 2024
A10: 06/03/2024 | B10: Azúcar | C10: Refinería Central | D10: 10 | E10: 35000 | F10: Marzo 2024
A11: 03/03/2024 | B11: Chocolate cobertura | C11: Chocolates Andinos | D11: 4 | E11: 68000 | F11: Marzo 2024
A12: 04/03/2024 | B12: Crema de leche | C12: Lácteos del Norte | D12: 6 | E12: 42000 | F12: Marzo 2024
A13: 05/04/2024 | B13: Café en grano | C13: Distribuidora La Cosecha | D13: 5 | E13: 75000 | F13: Abril 2024
A14: 06/04/2024 | B14: Leche entera | C14: Lácteos del Norte | D14: 20 | E14: 48000 | F14: Abril 2024
A15: 06/04/2024 | B15: Té verde surtido | C15: Importadora Oriente | D15: 3 | E15: 36000 | F15: Abril 2024
A16: 05/04/2024 | B16: Pan artesanal | C16: Panadería San Luis | D16: 10 | E16: 45000 | F16: Abril 2024
... A20: 04/04/2024 | B20: Crema de leche | C20: Lácteos del Norte | D20: 6 | E20: 42000 | F20: Abril 2024
A21: TOTAL COMPRAS | E21: =SUM(E5:E20)

Sheet Analisis
A1: ☕ CaféDigital — Hoja de Análisis
A2: Módulo 4 · Tablas resumen calculadas desde las hojas de datos
A4: 📊 Ventas por Producto | E4: ⭐ Satisfacción Promedio por Producto
A5: Producto | B5: Unidades Vendidas | C5: Ingresos (COP) | E5: Producto | F5: Calif. Promedio | G5: ¿Regresan? %
A6: Café expreso | B6: =SUMIF(Ventas!C:C,A6,Ventas!D:D) | C6: =SUMIF(Ventas!C:C,A6,Ventas!F:F) | E6: Café expreso | F6: =AVERAGEIF(Satisfaccion!C:C,E6,Satisfaccion!D:D) | G6: 87
A7: Capuchino | B7: =SUMIF(Ventas!C:C,A7,Ventas!D:D) | C7: =SUMIF(Ventas!C:C,A7,Ventas!F:F) | E7: Capuchino | F7: =AVERAGEIF(Satisfaccion!C:C,E7,Satisfaccion!D:D) | G7: 84
A8: Té frío | B8: =SUMIF(Ventas!C:C,A8,Ventas!D:D) | C8: =SUMIF(Ventas!C:C,A8,Ventas!F:F) | E8: Té frío | F8: =AVERAGEIF(Satisfaccion!C:C,E8,Satisfaccion!D:D) | G8: 81
A9: Sándwich | B9: =SUMIF(Ventas!C:C,A9,Ventas!D:D) | C9: =SUMIF(Ventas!C:C,A9,Ventas!F:F) | E9: Sándwich | F9: =AVERAGEIF(Satisfaccion!C:C,E9,Satisfaccion!D:D) | G9: 78
A10: Torta de chocolate | B10: =SUMIF(Ventas!C:C,A10,Ventas!D:D) | C10: =SUMIF(Ventas!C:C,A10,Ventas!F:F) | E10: Torta de chocolate | F10: =AVERAGEIF(Satisfaccion!C:C,E10,Satisfaccion!D:D) | G10: 75
A11: TOTAL | B11: =SUM(B6:B10) | C11: =SUM(C6:C10)
A13: 💰 Ingresos vs. Costos por Mes | E13: 🕐 Ventas por Franja Horaria
A14: Mes | B14: Ingresos (COP) | C14: Costos (COP) | E14: Franja | F14: Transacciones | G14: % del Total
A15: Marzo 2024 | B15: =SUMIF(Ventas!G:G,A15,Ventas!F:F) | C15: =SUMIF(Compras!F:F,A15,Compras!E:E) | E15: Mañana (7-10h) | F15: 38 | G15: =F15/SUM(F15:F19)
A16: Abril 2024 | B16: =SUMIF(Ventas!G:G,A16,Ventas!F:F) | C16: =SUMIF(Compras!F:F,A16,Compras!E:E) | E16: Media mañana (10-12h) | F16: 24 | G16: =F16/SUM(F15:F19)
A17: MARGEN ESTIMADO | B17: =SUM(B15:B16)-SUM(C15:C16) | C17: =B17/(SUM(B15:B16)) | E17: Almuerzo (12-14h) | F17: 31 | G17: =F17/SUM(F15:F19)
E18: Tarde (14-18h) | F18: 20 | G18: =F18/SUM(F15:F19)
E19: Cierre (18-19h) | F19: 7 | G19: =F19/SUM(F15:F19)
E20: TOTAL | F20: =SUM(F15:F19) | G20: 100%

Sheet Dashboard
A1: ☕ CaféDigital — Dashboard de Decisiones
A2: Período: Marzo – Abril 2024 | Actualización: Manual (reemplazar datos en hojas fuente)
A4: INGRESOS TOTALES | E4: SATISFACCIÓN PROMEDIO | I4: CLIENTES ATENDIDOS | M4: MARGEN ESTIMADO
A5: =SUM(Ventas!F:F)-Ventas!F1 | E5: =AVERAGE(Satisfaccion!D5:D1000) | I5: =COUNTA(Ventas!A5:A10000) | M5: =Analisis!C17
A50: 💡 NOTA: Para actualizar el dashboard, reemplaza los datos en las hojas Satisfaccion, Ventas y Compras. Los cálculos se actualizan automáticamente.
